<?xml version="1.0" encoding="ISO-8859-1"?>
<!DOCTYPE GDL SYSTEM "gdl.dtd">
<GDL>
<Form label="Links / rechts">
	<Group label="links" wy="0"> 
		<Text label="Name:" /> 
		<Text label="Straße:" /> 
		<Text label="PLZ/Ort:" />
	</Group> 
	<Group label="rechts" x="REL" y="0" wy="0"> 
		<Text label="Telefon:" /> 
		<Text label="Telefax:" /> 
		<Check label="privat" x="1" />
	</Group> 
	<Tabset>
		<Tab label="Aufträge">
			<Table>
				<Text label="Artikelbezeichnung" />
				<Date label="Datum" />
				<Number label="Anzahl" />
				<Money label="Betrag" />
			</Table>
		</Tab>
		<Tab label="Offene Posten">
		</Tab>
		<Tab label="Bankverbindung">
		</Tab>		
	</Tabset>
</Form>
</GDL>